{
    "name": "Raúl Guanca",
    "backImage" : "../assets/images/background_keyboard.jpg",
    "image" : "../assets/images/gabriel_r_guanca.jpg",
    "mainSkill" : "Full Stack Web Developer",
    "educationalIntitute" : {
         "name" : "Conicet",
         "img" : "../assets/images/conicet.png",
         "url" : "https://www.conicet.gov.ar/"
    },
    "program" : {
        "name" : "Argentina Programa",
        "img" : "../assets/images/Ap.png",
        "url" : "https://www.argentina.gob.ar/produccion/transformacion-digital-y-economia-del-conocimiento/argentina-programa"
    },
    "ubicacion" : "Tucumán (Argentina)",
    "about" : "Escritor y Desarrollador Web",
    "experience" : [{
        "position" : "Supervisor",
        "company" : "Teleperformance",
        "img" : "",
        "mode" : "",
        "start" : "",
        "end" : "",
        "timeElapsed" : ""
    }],
    "education" : [{
        "school" : "",
        "title" : "",
        "img" : "",
        "career" : "",
        "score" : 0,
        "start" : "",
        "end" : ""
    },
    {
        "school" : "",
        "title" : "",
        "img" : "",
        "career" : "",
        "score" : 0,
        "start" : "",
        "end" : ""
    }
    ],
    "aptitudes" : [{
        "name" : "HTML",
        "progress" : 75,
        "confirms" : 2,
        "confirmsNames" : [{
            "name" : "Raúl Guanca"
        }]
    },
    {
        "name" : "CSS",
        "progress" : 50,
        "confirms" : 3,
        "confirmsNames" : [{
            "name" : "Raúl Guanca"
        }]
    },
    {
        "name" : "JS",
        "progress" : 25,
        "confirms" : 4,
        "confirmsNames" : [{
            "name" : "Raúl Guanca"
        }]
    }
    ],
    "proyectos" : [{
        "name" : ""
    },
    {
        "name" : ""
    }    
   ]
  
}